nepali_roman/__init__.py
nepali_roman/romanize.py
nepali_roman-1.0.1.dist-info/LICENSE
nepali_roman-1.0.1.dist-info/METADATA
nepali_roman-1.0.1.dist-info/WHEEL
nepali_roman-1.0.1.dist-info/top_level.txt
nepali_roman-1.0.1.dist-info/RECORD
