Metadata-Version: 2.1
Name: nepali-roman
Version: 1.0.1
Summary: Convert Nepali text to roman English
Home-page: https://github.com/Suraj1127/nepali-roman
Author: Suraj Regmi
Author-email: regmi125@gmail.com
License: UNKNOWN
Platform: UNKNOWN
Classifier: Programming Language :: Python :: 3
Classifier: License :: OSI Approved :: MIT License
Classifier: Operating System :: OS Independent
